main2.py
query.py
catalogue/DatasetProfile.py
catalogue/FeatureProfileComputation.py
catalogue/__init__.py
constants/__init__.py
constants/defaults.py
constants/methods.py
constants/structure.py
data_retriever/DataRetriever.py
data_retriever/__init__.py
data_retriever-1.14.dist-info/licenses/LICENSE
database/Counter.py
database/Database.py
database/Execution.py
database/Operators.py
database/__init__.py
entities/ClinicalFeature.py
entities/ClinicalRecord.py
entities/Dataset.py
entities/DiagnosisFeature.py
entities/DiagnosisRecord.py
entities/Feature.py
entities/GenomicFeature.py
entities/GenomicRecord.py
entities/Hospital.py
entities/ImagingFeature.py
entities/ImagingRecord.py
entities/MedicineFeature.py
entities/MedicineRecord.py
entities/OntologyResource.py
entities/Patient.py
entities/PhenotypicFeature.py
entities/PhenotypicRecord.py
entities/Record.py
entities/Resource.py
entities/ResourceTest.py
entities/__init__.py
enums/AccessTypes.py
enums/AggregationTypes.py
enums/DataTypes.py
enums/DiagnosisColumns.py
enums/Domain.py
enums/EnumAsClass.py
enums/HospitalNames.py
enums/MetadataColumns.py
enums/Ontologies.py
enums/ParameterKeys.py
enums/Profile.py
enums/QueryTypes.py
enums/TableNames.py
enums/TheTestFiles.py
enums/TimerKeys.py
enums/UserAgents.py
enums/VcfColumns.py
enums/Visibility.py
enums/__init__.py
etl/ETL.py
etl/Extract.py
etl/Load.py
etl/Reporting.py
etl/Task.py
etl/Transform.py
etl/__init__.py
main_statistics/DatabaseStatistics.py
main_statistics/MainStatistics.py
main_statistics/QualityStatistics.py
main_statistics/TimeStatistics.py
main_statistics/__init__.py
preprocessing/Preprocess.py
preprocessing/PreprocessBuzziUC1.py
preprocessing/PreprocessCovid.py
preprocessing/PreprocessHsjd.py
preprocessing/PreprocessImgge.py
preprocessing/PreprocessKidneyCovid.py
preprocessing/PreprocessLafe.py
preprocessing/PreprocessingTask.py
preprocessing/__init__.py
utils/__init__.py
utils/api_utils.py
utils/cast_utils.py
utils/file_utils.py
utils/setup_logger.py
utils/str_utils.py
utils/test_utils.py
data_retriever-1.14.dist-info/METADATA
data_retriever-1.14.dist-info/WHEEL
data_retriever-1.14.dist-info/top_level.txt
data_retriever-1.14.dist-info/RECORD
