Metadata-Version: 2.4
Name: data_retriever
Version: 1.14
Summary: The package to retrieve data from ETL-built databases. Part of the BETTER project.
Author-email: Nelly Barret <nelly.barret@polimi.it>
License-Expression: MIT
Project-URL: Homepage, https://www.better-health-project.eu/
Project-URL: Issues, https://git.rwth-aachen.de/padme-development/external/better/data-cataloging/etl/-/issues
Classifier: Programming Language :: Python :: 3
Classifier: Operating System :: OS Independent
Requires-Python: >=3.9
License-File: LICENSE
Dynamic: license-file
